controller.v
`timescale 1ns/1ns
module Controller(input rst, zero, carry, clk, input[18:0] instruction, output reg reg2_read_source, mem_read_write, mem_or_alu, output reg  is_shift, output reg alu_src, update_z_c, reg_write_signal, stack_push, stack_pop, output reg [1:0] pc_src, output reg [1:0] scode, output reg [2:0] acode);
  
  initial begin
    update_z_c <= 0; reg2_read_source <= 0; mem_read_write <= 0; mem_or_alu <= 0; is_shift <= 0;
    alu_src <= 0; reg_write_signal <= 0; stack_push <= 0; stack_pop <= 0; pc_src <= 2'b0; scode <= 2'b0; acode <= 3'b0;
  end

  always @(posedge clk, instruction) begin //instruction commented
    //#1;
    reg2_read_source <= 0; mem_read_write <= 0; mem_or_alu <= 0; is_shift <= 0; alu_src <= 0; reg_write_signal <= 0; stack_push <= 0; stack_pop <= 0; pc_src <= 2'b0; scode <= 2'b0; acode <= 3'b0; update_z_c <= 0;

    $display(">>> alu src:  %d", alu_src);
    $display(">>> current instruction: %b", instruction);
    if(instruction == 19'b1111111111111111111) begin
      #5 $stop;
    end

    if(instruction[18:17] == 2'b00) begin
      $display(">>> normal R type!");
      $display(">>> alu src:  %d", alu_src);
      update_z_c <= 1;
      acode <= instruction[16:14];
      is_shift <= 0;
      alu_src <= 0;
      mem_or_alu <= 1;
      reg_write_signal <= 1;
    end
    
    if(instruction[18:17] == 2'b01) begin
      $display(">>> immediate R type!");
      update_z_c <= 1;
      acode <= instruction[16:14];
      is_shift <= 0;
      alu_src <= 1;
      mem_or_alu <= 1;
      reg_write_signal <= 1;
    end

    if(instruction[18:16] == 3'b110) begin
      $display(">>> shifting");
      scode <= instruction[15:14];
      is_shift <= 1;
      mem_or_alu <= 1;
      reg_write_signal <= 1;
      update_z_c <= 1;
    end

    if(instruction[18:16] == 3'b100) begin
      $display(">>> memory");
      reg2_read_source <= 1;
      mem_or_alu <= 0;
      alu_src <= 1;
      if(instruction[15:14] == 2'b00) begin //load
        mem_read_write <= 0;
        reg_write_signal <= 1;
      end else if(instruction[15:14] == 2'b01) begin // store
        mem_read_write <= 1;
      end
    end

    if(instruction[18:16] == 3'b101) begin
      $display(">>> beq");
      case(instruction[15:14])
        2'b00: pc_src <= (zero == 1 ? 2'b11 : 2'b00);
        2'b01: pc_src <= (zero == 0 ? 2'b11 : 2'b00);
        2'b10: pc_src <= (carry == 1 ? 2'b11 : 2'b00);
        2'b11: pc_src <= (carry == 0 ? 2'b11 : 2'b00);
      endcase
    end

    if(instruction[18:15] == 4'b1110) begin // jump without condition
      $display(">>> jump without condition!");
      if(instruction[14] == 1) stack_push <= 1; // jsb
      pc_src <= 2'b01; //jmp
    end

    if(instruction[18:13] == 6'b111100) begin // ret
      $display(">>> RET!");
      pc_src <= 2'b10;
      stack_pop <= 1;
    end
  end

endmodule

stack.v
`timescale 1ns/1ns
module Stack(input rst, push_sig, pop_sig, clk, input[11:0] push_data, output reg overflow, output reg [11:0] pop_data);
  
  initial begin
    overflow <= 0;
  end

  reg[11:0] data[7:0];
  reg[3:0] stack_pointer = 4'b0;
  
  always @(stack_pointer) begin
    if(stack_pointer != 4'b0) begin
        pop_data = data[stack_pointer - 1];
    end 
  end
  
  always @(posedge clk) begin
  //always @(posedge push_sig) begin
    if(push_sig) begin
      if(stack_pointer == 4'b1000) begin
        overflow <= 1;
      end else begin
        data[stack_pointer] <= push_data;
        stack_pointer <= stack_pointer + 1;
      end
    end
  end
  always @(posedge clk) begin
    if(pop_sig) begin
      if(stack_pointer != 4'b0) begin
        //pop_data <= data[stack_pointer - 1];
        stack_pointer <= stack_pointer - 1;
      end
    end
  end

  integer i;
  initial begin
    for(i = 0; i < 8; i = i + 1) begin: loop2
      $dumpvars(0, data[i]);
    end
  end
  
endmodule

data_memory.v
`timescale 1ns/1ns
module DataMemory(input rst, input[7:0] address, input[7:0] write_data, input read_write, clk, output reg[7:0] read_data);

  reg[7:0] data[255:0];

  always @(posedge clk) begin
    if(read_write & clk)
      data[address] <= write_data;
  end

  always @(address, read_write) begin
    if(read_write == 0) read_data = data[address];
  end

  integer i;
  initial begin
    for(i = 0; i < 6; i = i + 1) begin: loop
      $dumpvars(0, data[100+i]);
    end
  end

endmodule

alu.v
`timescale 1ns/1ns

module ALU(input rst, input signed [7:0] A, input signed [7:0] B, input carry_in, input is_shift, update_z_c, input [1:0] scode, input [2:0] acode, output reg [7:0] R, output reg zero, carry_out);

  function get_carry_out; input [7:0] A, B, C;
    get_carry_out = (A[7]&B[7]) | (A[7]^B[7])&~C[7];
  endfunction



  reg [8:0] temp;
  reg [15:0] temp2;
  reg [7:0] neg_B;
  initial begin
    zero = 0;
    carry_out = 0;
  end
  always @(A, B, scode, acode) begin
    neg_B = -B;
    case(is_shift)
      1'b0: begin
        case(acode)
          3'b000: begin
            temp = A + B;
            if(update_z_c == 1)
              carry_out = get_carry_out(A, B, temp);
          end
          3'b001: begin
            temp = A + B + carry_in; 
            if(update_z_c == 1)
              carry_out = get_carry_out(A, B+carry_in, temp);
          end
          3'b010: begin
            temp = A + ~B + 1;
            if(update_z_c == 1)
              carry_out = get_carry_out(A, -B, temp);
          end
          3'b011: begin
            temp = A + ~B + 1 - carry_in;
            if(update_z_c == 1)
              carry_out = get_carry_out(A, -B + carry_in, temp);
          end

          3'b100: temp = A & B;
          3'b101: temp = A | B;
          3'b110: temp = A ^ B;
          3'b111: temp = ~(A & B);
        endcase
        R = temp[7:0];
      end
      1'b1: 
        if(B == 8'b0)
          R = A;
        else begin
          case(scode)
            2'b00: begin
              carry_out = A[8-B];
              R = A <<< B;
            end
            2'b01: begin
              carry_out = A[B-1];
              R = A >>> B;
            end
            2'b10: begin
              temp2 = {A,A} << (B);
              R = temp2[15:8];
              carry_out = A[7-B];
            end
            2'b11: begin
              temp2 = {A,A} >> (B);
              R = temp2[7:0];
              carry_out = A[B-1];
            end
          endcase
        end
    endcase
    if(update_z_c == 1)
      zero = (R == 8'b0);
  end
endmodule

register_file.v
`timescale 1ns/1ns
module RegisterFile(input rst, input[2:0] reg_read_1, input [2:0] reg_read_2, input [2:0] reg_write, input reg_write_signal, clk, input[7:0] in_data, output reg [7:0] out_data_1, output reg [7:0] out_data_2);
  
  reg[7:0] registers[7:0];
  always @(posedge clk) begin
    if(reg_write_signal & clk) begin
      registers[reg_write] <= in_data;
    end
  end
  
  initial begin
    out_data_1 = registers[reg_read_1];
    out_data_2 = registers[reg_read_2];
    registers[0] = 0; //$R0
  end
  
  always @(reg_read_1, reg_read_2) begin
    out_data_1 = registers[reg_read_1];
    out_data_2 = registers[reg_read_2];
    registers[0] = 0; //$R0
  end
  
  integer i;
  always @(clk) begin
    for(i = 0; i < 8; i = i + 1) begin: loop
      $display("register[%d]:  %b", i, registers[i]);
    end
  end

  initial begin
    for(i = 0; i < 8; i = i + 1) begin: loop2
      $dumpvars(0, registers[i]);
    end
  end
  
  
endmodule

instruction_memory.v
`timescale 1ns/1ns
module InstructionMemory(input rst, input[11:0] address, output reg[18:0] instruction);
  reg[18:0] instructions[4095:0];

  initial begin
    $readmemb("instructions.mips", instructions);
  end

  always @(address) begin
    instruction = instructions[address];
  end
endmodule

data_path.v
`timescale 1ns/1ns
module DataPath(input rst, reg2_read_source, mem_read_write, mem_or_alu, input is_shift, input alu_src, update_z_c, reg_write_signal, stack_push, stack_pop, clk, input [1:0] pc_src, input [1:0] scode, input [2:0] acode, output zero, stack_overflow, output reg carry, output [18:0] instruction);

  reg[11:0] pc = 12'b0;
  wire[7:0] reg_out_1, reg_out_2;
  wire alu_carry_out;
  wire[7:0] alu_result, data_memory_out;
  wire[11:0] stack_out;
  reg x; 
  
  always @(posedge clk) begin
    if (update_z_c==1) 
      carry <= alu_carry_out;
      case(pc_src)
        2'b00: pc <= pc + 1;
        2'b01: pc <= instruction[11:0];
        2'b10: pc <= stack_out;
        2'b11: pc <= pc + 1 + {{4{instruction[7]}},instruction[7:0]};
      endcase
  end

  always @(reg_out_1) begin
    $display("reg_out_1:  %b", reg_out_1);
  end

  InstructionMemory instruction_memory(rst, pc, instruction);

  RegisterFile register_file(rst, instruction[10:8], reg2_read_source ? instruction[13:11] : instruction[7:5], instruction[13:11],reg_write_signal, clk, mem_or_alu ? alu_result : data_memory_out, reg_out_1, reg_out_2);
  
  ALU alu(rst, reg_out_1, (alu_src ? instruction[7:0] : ( is_shift ? {5'b0,instruction[7:5]} : reg_out_2)), carry, is_shift, update_z_c, scode, acode, alu_result, zero, alu_carry_out);

  DataMemory data_memory(rst, alu_result, reg_out_2, mem_read_write, clk, data_memory_out);

  Stack stack(rst, stack_push, stack_pop, clk, pc + {11'b0,1'b1}, stack_overflow, stack_out);

endmodule

CPU.v
`timescale 1ns/1ns
module MIPSCPU(input clk, rst, output zero, carry, stack_overflow);
  wire reg2_read_source, mem_read_write, mem_or_alu;
  wire is_shift;
  wire alu_src, update_z_c, reg_read_write, stack_pushs, stack_pop;
  wire [1:0] pc_src, scode;
  wire [2:0] acode;
  wire [18:0] instruction;

  DataPath data_path(rst, reg2_read_source, mem_read_write, mem_or_alu, is_shift, alu_src, update_z_c, reg_read_write, stack_push, stack_pop, clk, pc_src, scode, acode, zero, stack_overflow, carry, instruction);

  Controller controller(rst, zero, carry, clk, instruction, reg2_read_source, mem_read_write, mem_or_alu, is_shift, alu_src, update_z_c, reg_read_write, stack_push, stack_pop, pc_src, scode, acode);

endmodule

tests/CPU_test.v
`timescale 1ns/1ns

module CPUTest;
  reg clk = 0, rst;
  wire zero, carry, stack_overflow;

  MIPSCPU cpu(clk, rst, zero, carry, stack_overflow);

  always begin
    #20 clk = ~clk;
    //if(clk == 1) begin
      //$display("");
      //$display("-------------------------------------------------------");
      //$display("a clock pulse passed!");
      //$display("-------------------------------------------------------");
      //$display("");
    //end
  end

  initial begin
    $dumpfile("cpu.vcd");
    $dumpvars(0, CPUTest);
  end
endmodule

dump.vcd
$date
	Thu Apr 16 12:26:54 2015
$end
$version
	Icarus Verilog
$end
$timescale
	1ns
$end
$scope module CPUTest $end
$scope module cpu $end
$scope module data_path $end
$scope module register_file $end
$var reg 8 ! \registers[0] [7:0] $end
$upscope $end
$upscope $end
$upscope $end
$upscope $end
$scope module CPUTest $end
$scope module cpu $end
$scope module data_path $end
$scope module register_file $end
$var reg 8 " \registers[1] [7:0] $end
$upscope $end
$upscope $end
$upscope $end
$upscope $end
$scope module CPUTest $end
$scope module cpu $end
$scope module data_path $end
$scope module register_file $end
$var reg 8 # \registers[2] [7:0] $end
$upscope $end
$upscope $end
$upscope $end
$upscope $end
$scope module CPUTest $end
$scope module cpu $end
$scope module data_path $end
$scope module register_file $end
$var reg 8 $ \registers[3] [7:0] $end
$upscope $end
$upscope $end
$upscope $end
$upscope $end
$scope module CPUTest $end
$scope module cpu $end
$scope module data_path $end
$scope module register_file $end
$var reg 8 % \registers[4] [7:0] $end
$upscope $end
$upscope $end
$upscope $end
$upscope $end
$scope module CPUTest $end
$scope module cpu $end
$scope module data_path $end
$scope module register_file $end
$var reg 8 & \registers[5] [7:0] $end
$upscope $end
$upscope $end
$upscope $end
$upscope $end
$scope module CPUTest $end
$scope module cpu $end
$scope module data_path $end
$scope module register_file $end
$var reg 8 ' \registers[6] [7:0] $end
$upscope $end
$upscope $end
$upscope $end
$upscope $end
$scope module CPUTest $end
$scope module cpu $end
$scope module data_path $end
$scope module register_file $end
$var reg 8 ( \registers[7] [7:0] $end
$upscope $end
$upscope $end
$upscope $end
$upscope $end
$scope module CPUTest $end
$scope module cpu $end
$scope module data_path $end
$scope module data_memory $end
$var reg 8 ) \data[100] [7:0] $end
$upscope $end
$upscope $end
$upscope $end
$upscope $end
$scope module CPUTest $end
$scope module cpu $end
$scope module data_path $end
$scope module data_memory $end
$var reg 8 * \data[101] [7:0] $end
$upscope $end
$upscope $end
$upscope $end
$upscope $end
$scope module CPUTest $end
$scope module cpu $end
$scope module data_path $end
$scope module data_memory $end
$var reg 8 + \data[102] [7:0] $end
$upscope $end
$upscope $end
$upscope $end
$upscope $end
$scope module CPUTest $end
$scope module cpu $end
$scope module data_path $end
$scope module data_memory $end
$var reg 8 , \data[103] [7:0] $end
$upscope $end
$upscope $end
$upscope $end
$upscope $end
$scope module CPUTest $end
$scope module cpu $end
$scope module data_path $end
$scope module data_memory $end
$var reg 8 - \data[104] [7:0] $end
$upscope $end
$upscope $end
$upscope $end
$upscope $end
$scope module CPUTest $end
$scope module cpu $end
$scope module data_path $end
$scope module data_memory $end
$var reg 8 . \data[105] [7:0] $end
$upscope $end
$upscope $end
$upscope $end
$upscope $end
$scope module CPUTest $end
$scope module cpu $end
$scope module data_path $end
$scope module stack $end
$var reg 12 / \data[0] [11:0] $end
$upscope $end
$upscope $end
$upscope $end
$upscope $end
$scope module CPUTest $end
$scope module cpu $end
$scope module data_path $end
$scope module stack $end
$var reg 12 0 \data[1] [11:0] $end
$upscope $end
$upscope $end
$upscope $end
$upscope $end
$scope module CPUTest $end
$scope module cpu $end
$scope module data_path $end
$scope module stack $end
$var reg 12 1 \data[2] [11:0] $end
$upscope $end
$upscope $end
$upscope $end
$upscope $end
$scope module CPUTest $end
$scope module cpu $end
$scope module data_path $end
$scope module stack $end
$var reg 12 2 \data[3] [11:0] $end
$upscope $end
$upscope $end
$upscope $end
$upscope $end
$scope module CPUTest $end
$scope module cpu $end
$scope module data_path $end
$scope module stack $end
$var reg 12 3 \data[4] [11:0] $end
$upscope $end
$upscope $end
$upscope $end
$upscope $end
$scope module CPUTest $end
$scope module cpu $end
$scope module data_path $end
$scope module stack $end
$var reg 12 4 \data[5] [11:0] $end
$upscope $end
$upscope $end
$upscope $end
$upscope $end
$scope module CPUTest $end
$scope module cpu $end
$scope module data_path $end
$scope module stack $end
$var reg 12 5 \data[6] [11:0] $end
$upscope $end
$upscope $end
$upscope $end
$upscope $end
$scope module CPUTest $end
$scope module cpu $end
$scope module data_path $end
$scope module stack $end
$var reg 12 6 \data[7] [11:0] $end
$upscope $end
$upscope $end
$upscope $end
$upscope $end
$scope module CPUTest $end
$var wire 1 7 carry $end
$var wire 1 8 stack_overflow $end
$var wire 1 9 zero $end
$var reg 1 : clk $end
$var reg 1 ; rst $end
$scope module cpu $end
$var wire 3 < acode [2:0] $end
$var wire 1 = alu_src $end
$var wire 1 7 carry $end
$var wire 1 > clk $end
$var wire 19 ? instruction [18:0] $end
$var wire 1 @ is_shift $end
$var wire 1 A mem_or_alu $end
$var wire 1 B mem_read_write $end
$var wire 2 C pc_src [1:0] $end
$var wire 1 D reg2_read_source $end
$var wire 1 E reg_read_write $end
$var wire 1 F rst $end
$var wire 2 G scode [1:0] $end
$var wire 1 8 stack_overflow $end
$var wire 1 H stack_pop $end
$var wire 1 I stack_push $end
$var wire 1 J update_z_c $end
$var wire 1 9 zero $end
$scope module data_path $end
$var wire 3 K acode [2:0] $end
$var wire 1 L alu_carry_out $end
$var wire 8 M alu_result [7:0] $end
$var wire 1 = alu_src $end
$var wire 1 > clk $end
$var wire 8 N data_memory_out [7:0] $end
$var wire 19 O instruction [18:0] $end
$var wire 1 @ is_shift $end
$var wire 1 A mem_or_alu $end
$var wire 1 B mem_read_write $end
$var wire 2 P pc_src [1:0] $end
$var wire 1 D reg2_read_source $end
$var wire 8 Q reg_out_1 [7:0] $end
$var wire 8 R reg_out_2 [7:0] $end
$var wire 1 E reg_write_signal $end
$var wire 1 F rst $end
$var wire 2 S scode [1:0] $end
$var wire 12 T stack_out [11:0] $end
$var wire 1 8 stack_overflow $end
$var wire 1 H stack_pop $end
$var wire 1 I stack_push $end
$var wire 1 J update_z_c $end
$var wire 1 9 zero $end
$var reg 1 U carry $end
$var reg 12 V pc [11:0] $end
$scope module instruction_memory $end
$var wire 12 W address [11:0] $end
$var wire 1 F rst $end
$var reg 19 X instruction [18:0] $end
$upscope $end
$scope module register_file $end
$var wire 1 > clk $end
$var wire 8 Y in_data [7:0] $end
$var wire 3 Z reg_read_1 [2:0] $end
$var wire 3 [ reg_read_2 [2:0] $end
$var wire 3 \ reg_write [2:0] $end
$var wire 1 E reg_write_signal $end
$var wire 1 F rst $end
$var integer 32 ] i [31:0] $end
$var reg 8 ^ out_data_1 [7:0] $end
$var reg 8 _ out_data_2 [7:0] $end
$scope begin loop $end
$upscope $end
$scope begin loop2 $end
$upscope $end
$upscope $end
$scope module alu $end
$var wire 8 ` A [7:0] $end
$var wire 8 a B [7:0] $end
$var wire 3 b acode [2:0] $end
$var wire 1 7 carry_in $end
$var wire 1 @ is_shift $end
$var wire 1 F rst $end
$var wire 2 c scode [1:0] $end
$var wire 1 J update_z_c $end
$var reg 8 d R [7:0] $end
$var reg 1 e carry_out $end
$var reg 8 f neg_B [7:0] $end
$var reg 9 g temp [8:0] $end
$var reg 16 h temp2 [15:0] $end
$var reg 1 i zero $end
$scope function get_carry_out $end
$var reg 8 j A [7:0] $end
$var reg 8 k B [7:0] $end
$var reg 8 l C [7:0] $end
$var reg 1 m get_carry_out $end
$upscope $end
$upscope $end
$scope module data_memory $end
$var wire 8 n address [7:0] $end
$var wire 1 > clk $end
$var wire 1 B read_write $end
$var wire 1 F rst $end
$var wire 8 o write_data [7:0] $end
$var integer 32 p i [31:0] $end
$var reg 8 q read_data [7:0] $end
$scope begin loop $end
$upscope $end
$upscope $end
$scope module stack $end
$var wire 1 > clk $end
$var wire 1 H pop_sig $end
$var wire 12 r push_data [11:0] $end
$var wire 1 I push_sig $end
$var wire 1 F rst $end
$var integer 32 s i [31:0] $end
$var reg 1 t overflow $end
$var reg 12 u pop_data [11:0] $end
$var reg 4 v stack_pointer [3:0] $end
$scope begin loop2 $end
$upscope $end
$upscope $end
$upscope $end
$scope module controller $end
$var wire 1 7 carry $end
$var wire 1 > clk $end
$var wire 19 w instruction [18:0] $end
$var wire 1 F rst $end
$var wire 1 9 zero $end
$var reg 3 x acode [2:0] $end
$var reg 1 y alu_src $end
$var reg 1 z is_shift $end
$var reg 1 { mem_or_alu $end
$var reg 1 | mem_read_write $end
$var reg 2 } pc_src [1:0] $end
$var reg 1 ~ reg2_read_source $end
$var reg 1 !" reg_write_signal $end
$var reg 2 "" scode [1:0] $end
$var reg 1 #" stack_pop $end
$var reg 1 $" stack_push $end
$var reg 1 %" update_z_c $end
$upscope $end
$upscope $end
$upscope $end
$enddefinitions $end
#0
$dumpvars
1%"
0$"
0#"
b0 ""
1!"
0~
b0 }
0|
1{
0z
1y
b0 x
b100000100000000001 w
b0 v
bx u
0t
b1000 s
b1 r
bx q
b110 p
b0 o
b1 n
0m
b1 l
b1 k
b0 j
0i
bx h
b1 g
b11111111 f
0e
b1 d
b0 c
b0 b
b1 a
b0 `
b0 _
b0 ^
b1000 ]
b1 \
b0 [
b0 Z
b1 Y
b100000100000000001 X
b0 W
b0 V
xU
bx T
b0 S
b0 R
b0 Q
b0 P
b100000100000000001 O
bx N
b1 M
0L
b0 K
1J
0I
0H
b0 G
xF
1E
0D
b0 C
0B
1A
0@
b100000100000000001 ?
0>
1=
b0 <
x;
0:
09
08
x7
bx 6
bx 5
bx 4
bx 3
bx 2
bx 1
bx 0
bx /
bx .
bx -
bx ,
bx +
bx *
bx )
bx (
bx '
bx &
bx %
bx $
bx #
bx "
b0 !
$end
#20
1|
1B
1~
1D
bx Y
b1100100 d
b1100100 M
b1100100 n
b1100100 l
b1100100 k
b1100100 g
b10011100 f
b0 !
b1 _
b1 R
b1 o
b1100100 a
b1 [
b1000100100001100100 X
b1000100100001100100 ?
b1000100100001100100 O
b1000100100001100100 w
0%"
0J
0!"
0E
1y
1=
0{
0A
b1 "
b1 V
b10 r
b1 W
0U
07
b1000 ]
1:
1>
#40
b1000 ]
0:
0>
#60
b0 !
b0 _
b0 R
b0 o
b10 Y
b0 [
1!"
1E
1{
1A
1%"
1J
b10 d
b10 M
b10 n
b10 g
b11111110 f
b10 a
b100000100000000010 X
b100000100000000010 ?
b100000100000000010 O
b100000100000000010 w
1y
1=
0|
0B
0~
0D
b10 V
b11 r
b10 W
b1 )
b1000 ]
1:
1>
#80
b1000 ]
0:
0>
#100
1|
1B
1~
1D
bx Y
b1100101 d
b1100101 M
b1100101 n
b1100101 l
b1100101 k
b1100101 g
b10011011 f
b0 !
b10 _
b10 R
b10 o
b1100101 a
b1 [
b1000100100001100101 X
b1000100100001100101 ?
b1000100100001100101 O
b1000100100001100101 w
0%"
0J
0!"
0E
1y
1=
0{
0A
b10 "
b11 V
b100 r
b11 W
b1000 ]
1:
1>
#120
b1000 ]
0:
0>
#140
b0 !
b0 _
b0 R
b0 o
b11 Y
b0 [
1!"
1E
1{
1A
1%"
1J
b11 d
b11 M
b11 n
b11 g
b11111101 f
b11 a
b100000100000000011 X
b100000100000000011 ?
b100000100000000011 O
b100000100000000011 w
1y
1=
0|
0B
0~
0D
b100 V
b101 r
b100 W
b10 *
b1000 ]
1:
1>
#160
b1000 ]
0:
0>
#180
1|
1B
1~
1D
bx Y
b1100110 d
b1100110 M
b1100110 n
b1100110 l
b1100110 k
b1100110 g
b10011010 f
b0 !
b11 _
b11 R
b11 o
b1100110 a
b1 [
b1000100100001100110 X
b1000100100001100110 ?
b1000100100001100110 O
b1000100100001100110 w
0%"
0J
0!"
0E
1y
1=
0{
0A
b11 "
b101 V
b110 r
b101 W
b1000 ]
1:
1>
#200
b1000 ]
0:
0>
#220
b0 !
b0 _
b0 R
b0 o
b100 Y
b0 [
1!"
1E
1{
1A
1%"
1J
b100 d
b100 M
b100 n
b100 g
b11111100 f
b100 a
b100000100000000100 X
b100000100000000100 ?
b100000100000000100 O
b100000100000000100 w
1y
1=
0|
0B
0~
0D
b110 V
b111 r
b110 W
b11 +
b1000 ]
1:
1>
#240
b1000 ]
0:
0>
#260
1|
1B
1~
1D
bx Y
b1100111 d
b1100111 M
b1100111 n
b1100111 l
b1100111 k
b1100111 g
b10011001 f
b0 !
b100 _
b100 R
b100 o
b1100111 a
b1 [
b1000100100001100111 X
b1000100100001100111 ?
b1000100100001100111 O
b1000100100001100111 w
0%"
0J
0!"
0E
1y
1=
0{
0A
b100 "
b111 V
b1000 r
b111 W
b1000 ]
1:
1>
#280
b1000 ]
0:
0>
#300
b0 !
b0 _
b0 R
b0 o
b101 Y
b0 [
1!"
1E
1{
1A
1%"
1J
b101 d
b101 M
b101 n
b101 g
b11111011 f
b101 a
b100000100000000101 X
b100000100000000101 ?
b100000100000000101 O
b100000100000000101 w
1y
1=
0|
0B
0~
0D
b1000 V
b1001 r
b1000 W
b100 ,
b1000 ]
1:
1>
#320
b1000 ]
0:
0>
#340
1|
1B
1~
1D
bx Y
b1101000 d
b1101000 M
b1101000 n
b1101000 l
b1101000 k
b1101000 g
b10011000 f
b0 !
b101 _
b101 R
b101 o
b1101000 a
b1 [
b1000100100001101000 X
b1000100100001101000 ?
b1000100100001101000 O
b1000100100001101000 w
0%"
0J
0!"
0E
1y
1=
0{
0A
b101 "
b1001 V
b1010 r
b1001 W
b1000 ]
1:
1>
#360
b1000 ]
0:
0>
#380
1i
19
0e
0L
0m
b0 l
b0 k
b0 Y
1!"
1E
1{
1A
1%"
1J
b0 d
b0 M
b0 n
b0 g
b0 f
b0 !
b0 _
b0 R
b0 o
b0 a
b0 [
b111 \
b11100000000000 X
b11100000000000 ?
b11100000000000 O
b11100000000000 w
0y
0=
0|
0B
0~
0D
b1010 V
b1011 r
b1010 W
b101 -
b1000 ]
1:
1>
#400
b1000 ]
0:
0>
#420
b1 \
b100000000000 X
b100000000000 ?
b100000000000 O
b100000000000 w
1%"
1J
1!"
1E
1{
1A
b0 (
b1011 V
b1100 r
b1011 W
b1000 ]
1:
1>
#440
b1000 ]
0:
0>
#460
b11111011 Y
0i
09
b11111011 d
b11111011 M
b11111011 n
b11111011 l
b11111011 k
b111111011 g
b11111011 f
b101 a
1y
1=
b10 x
b10 <
b10 K
b10 b
b0 !
b11 \
b1 Z
b101001100100000101 X
b101001100100000101 ?
b101001100100000101 O
b101001100100000101 w
1%"
1J
1!"
1E
1{
1A
b1100 V
b1101 r
b1100 W
b0 "
b1000 ]
1:
1>
#480
b1000 ]
0:
0>
#500
bx Y
b0 d
b0 M
b0 n
b11111010 l
b11111010 k
b0 g
b0 f
b0 a
b0 !
b0 \
b0 Z
b1010000000000000110 X
b1010000000000000110 ?
b1010000000000000110 O
b1010000000000000110 w
0%"
0J
b0 x
b0 <
b0 K
b0 b
0!"
0E
0y
0=
0{
0A
b11111011 $
b1101 V
b1110 r
b1101 W
b1000 ]
1:
1>
#520
b1000 ]
0:
0>
#540
b1 Y
b1 q
b1 N
1!"
1E
1y
1=
1~
1D
b1100100 d
b1100100 M
b1100100 n
b1100100 g
b10011100 f
b1100100 a
bx _
bx R
bx o
b10 [
b0 !
b10 \
b1 Z
b1000001000101100100 X
b1000001000101100100 ?
b1000001000101100100 O
b1000001000101100100 w
b1110 V
b1111 r
b1110 W
b1000 ]
1:
1>
#560
b1000 ]
0:
0>
#580
b11111111 l
b11111111 k
1{
1A
b10 x
b10 <
b10 K
b10 b
1%"
1J
b11111111 Y
bx q
bx N
b11111111 d
b11111111 M
b11111111 n
b111111111 g
b11111111 f
b1 a
b10 [
b0 !
b1 _
b1 R
b1 o
b11 \
b111 Z
b1001111101000000 X
b1001111101000000 ?
b1001111101000000 O
b1001111101000000 w
1!"
1E
0y
0=
0~
0D
b1 #
b1111 V
b10000 r
b1111 W
b1000 ]
1:
1>
#600
b1000 ]
0:
0>
#620
bx Y
1i
19
b0 d
b0 M
b0 n
b0 l
b0 k
b0 g
b0 f
b0 a
b0 _
b0 R
b0 o
b0 [
b0 !
b0 \
b0 Z
b1011000000000000001 X
b1011000000000000001 ?
b1011000000000000001 O
b1011000000000000001 w
0%"
0J
b0 x
b0 <
b0 K
b0 b
0!"
0E
0{
0A
b10000 V
b10001 r
b10000 W
b11111111 $
b1000 ]
1:
1>
#640
b1000 ]
0:
0>
#660
b1 Y
1!"
1E
1{
1A
1%"
1J
b1 d
b1 M
b1 n
b1 g
b0 !
b1 ^
b1 Q
b1 `
b111 \
b10 Z
b11101000000000 X
b11101000000000 ?
b11101000000000 O
b11101000000000 w
b10001 V
b10010 r
b10001 W
b1000 ]
1:
1>
#680
b1000 ]
0:
0>
#700
0i
09
b1 l
b1 k
b11111111 f
b1 a
1y
1=
b1 Y
b1 d
b1 M
b1 n
b1 g
b0 !
b0 ^
b0 Q
b0 `
b1 \
b1 Z
b100000100100000001 X
b100000100100000001 ?
b100000100100000001 O
b100000100100000001 w
1%"
1J
1!"
1E
1{
1A
b10010 V
b10011 r
b10010 W
b1 (
b1000 ]
1:
1>
#720
b1000 ]
0:
0>
#740
b1 }
b1 C
b1 P
bx Y
b0 d
b0 M
b0 n
b1100 l
b1100 k
b0 g
b0 f
b0 a
b0 !
b0 \
b0 Z
b1110000000000001100 X
b1110000000000001100 ?
b1110000000000001100 O
b1110000000000001100 w
0%"
0J
0!"
0E
0y
0=
0{
0A
b1 "
b10011 V
b10100 r
b10011 W
b1000 ]
1:
1>
#760
b1000 ]
0:
0>
#780
b11111011 f
b11111100 Y
b101 a
b11111100 l
b11111011 k
b1 j
1!"
1E
1{
1A
1y
1=
b10 x
b10 <
b10 K
b10 b
1%"
1J
b11111100 d
b11111100 M
b11111100 n
b111111100 g
b0 !
b1 ^
b1 Q
b1 `
b11 \
b1 Z
b101001100100000101 X
b101001100100000101 ?
b101001100100000101 O
b101001100100000101 w
b0 }
b0 C
b0 P
b1100 V
b1101 r
b1100 W
b1000 ]
1:
1>
#800
b1000 ]
0:
0>
#820
bx Y
b0 d
b0 M
b0 n
b11111010 l
b11111010 k
b0 j
b0 g
b0 f
b0 a
b0 !
b0 ^
b0 Q
b0 `
b0 \
b0 Z
b1010000000000000110 X
b1010000000000000110 ?
b1010000000000000110 O
b1010000000000000110 w
0%"
0J
b0 x
b0 <
b0 K
b0 b
0!"
0E
0y
0=
0{
0A
b11111100 $
b1101 V
b1110 r
b1101 W
b1000 ]
1:
1>
#840
b1000 ]
0:
0>
#860
b10 Y
b10 q
b10 N
1!"
1E
1y
1=
1~
1D
b10011100 f
b1100100 a
b1 _
b1 R
b1 o
b1100101 d
b1100101 M
b1100101 n
b1100101 g
b10 [
b0 !
b1 ^
b1 Q
b1 `
b10 \
b1 Z
b1000001000101100100 X
b1000001000101100100 ?
b1000001000101100100 O
b1000001000101100100 w
b1110 V
b1111 r
b1110 W
b1000 ]
1:
1>
#880
b1000 ]
0:
0>
#900
b11111111 l
b11111110 k
b1 j
1{
1A
b10 x
b10 <
b10 K
b10 b
1%"
1J
b11111111 Y
bx q
bx N
b11111111 d
b11111111 M
b11111111 n
b111111111 g
b11111110 f
b10 a
b10 [
b0 !
b10 _
b10 R
b10 o
b11 \
b111 Z
b1001111101000000 X
b1001111101000000 ?
b1001111101000000 O
b1001111101000000 w
1!"
1E
0y
0=
0~
0D
b10 #
b1111 V
b10000 r
b1111 W
b1000 ]
1:
1>
#920
b1000 ]
0:
0>
#940
1i
19
b0 k
b0 f
b0 a
bx Y
b0 _
b0 R
b0 o
b0 d
b0 M
b0 n
b0 l
b0 j
b0 g
b0 [
b0 !
b0 ^
b0 Q
b0 `
b0 \
b0 Z
b1011000000000000001 X
b1011000000000000001 ?
b1011000000000000001 O
b1011000000000000001 w
0%"
0J
b0 x
b0 <
b0 K
b0 b
0!"
0E
0{
0A
b10000 V
b10001 r
b10000 W
b11111111 $
b1000 ]
1:
1>
#960
b1000 ]
0:
0>
#980
b10 Y
1!"
1E
1{
1A
1%"
1J
b10 d
b10 M
b10 n
b10 g
b0 !
b10 ^
b10 Q
b10 `
b111 \
b10 Z
b11101000000000 X
b11101000000000 ?
b11101000000000 O
b11101000000000 w
b10001 V
b10010 r
b10001 W
b1000 ]
1:
1>
#1000
b1000 ]
0:
0>
