controller.v
`timescale 1ns/1ns
module Controller(input rst, zero, carry, clk, input is_halt, input[18:0] instruction, output reg reg2_read_source, mem_read_write, mem_or_alu, output reg  is_shift, output reg alu_src, update_z_c, reg_write_signal, stack_push, stack_pop, output reg [1:0] pc_src, output reg [1:0] scode, output reg [2:0] acode);
  
  initial begin
    update_z_c <= 0; reg2_read_source <= 0; mem_read_write <= 0; mem_or_alu <= 0; is_shift <= 0;
    alu_src <= 0; reg_write_signal <= 0; stack_push <= 0; stack_pop <= 0; pc_src <= 2'b0; scode <= 2'b0; acode <= 3'b0;
  end

  always @(posedge clk, instruction) begin //instruction commented
    //#1;
    reg2_read_source <= 0; mem_read_write <= 0; mem_or_alu <= 0; is_shift <= 0; alu_src <= 0; reg_write_signal <= 0; stack_push <= 0; stack_pop <= 0; pc_src <= 2'b0; scode <= 2'b0; acode <= 3'b0; update_z_c <= 0;

    $display(">>> alu src:  %d", alu_src);
    $display(">>> current instruction: %b", instruction);
    //if(instruction == 19'b1111111111111111111) begin
    if(is_halt == 1'b1) begin 
      #5 $finish;
    end

    if(instruction[18:17] == 2'b00) begin
      $display(">>> normal R type!");
      $display(">>> alu src:  %d", alu_src);
      update_z_c <= 1;
      acode <= instruction[16:14];
      is_shift <= 0;
      alu_src <= 0;
      mem_or_alu <= 1;
      reg_write_signal <= 1;
    end
    
    if(instruction[18:17] == 2'b01) begin
      $display(">>> immediate R type!");
      update_z_c <= 1;
      acode <= instruction[16:14];
      is_shift <= 0;
      alu_src <= 1;
      mem_or_alu <= 1;
      reg_write_signal <= 1;
    end

    if(instruction[18:16] == 3'b110) begin
      $display(">>> shifting");
      scode <= instruction[15:14];
      is_shift <= 1;
      mem_or_alu <= 1;
      reg_write_signal <= 1;
      update_z_c <= 1;
    end

    if(instruction[18:16] == 3'b100) begin
      $display(">>> memory");
      reg2_read_source <= 1;
      mem_or_alu <= 0;
      alu_src <= 1;
      if(instruction[15:14] == 2'b00) begin //load
        mem_read_write <= 0;
        reg_write_signal <= 1;
      end else if(instruction[15:14] == 2'b01) begin // store
        mem_read_write <= 1;
      end
    end

    if(instruction[18:16] == 3'b101) begin
      $display(">>> beq");
      case(instruction[15:14])
        2'b00: pc_src <= (zero == 1 ? 2'b11 : 2'b00);
        2'b01: pc_src <= (zero == 0 ? 2'b11 : 2'b00);
        2'b10: pc_src <= (carry == 1 ? 2'b11 : 2'b00);
        2'b11: pc_src <= (carry == 0 ? 2'b11 : 2'b00);
      endcase
    end

    if(instruction[18:15] == 4'b1110) begin // jump without condition
      $display(">>> jump without condition!");
      if(instruction[14] == 1) stack_push <= 1; // jsb
      pc_src <= 2'b01; //jmp
    end

    if(instruction[18:13] == 6'b111100) begin // ret
      $display(">>> RET!");
      pc_src <= 2'b10;
      stack_pop <= 1;
    end
  end

endmodule

forwarding_unit.v
`timescale 1ns/1ns
module ForwardingUnit(input reg2_read_source, EX_reg_write_signal, input[18:0] EX_inst, input[18:0] ID_inst, input MEM_reg_write_signal, input[18:0] MEM_inst, output reg[1:0] forward_A, output reg[1:0] forward_B);

  initial begin
    forward_A = 2'b00;
    forward_B = 2'b00;
  end
  /* EX hazard */
  always @(EX_reg_write_signal, EX_inst, ID_inst, MEM_reg_write_signal, MEM_inst) begin
    forward_A = 2'b00;
    forward_B = 2'b00;

    if(EX_reg_write_signal == 1'b1 & (EX_inst[13:11] != 3'b000) & (EX_inst[13:11] == ID_inst[10:8]))
      forward_A = 2'b01;
   
    if(EX_reg_write_signal & (EX_inst[13:11] != 3'b000) & (EX_inst[13:11] == (reg2_read_source ? ID_inst[10:8] : ID_inst[7:5])))
      forward_B = 2'b01;


  /* MEM hazard */
    if(MEM_reg_write_signal == 1'b1 & (MEM_inst[13:11] != 3'b000) & ~(EX_reg_write_signal == 1'b1 & (EX_inst[13:11] != 3'b000) & (EX_inst[13:11] == ID_inst[10:8])) & (MEM_inst[13:11] == ID_inst[10:8]))
      forward_A = 2'b10;

    if(MEM_reg_write_signal == 1'b1 & (MEM_inst[13:11] != 3'b000)
  & 
~(EX_reg_write_signal & (EX_inst[13:11] != 3'b000) & (EX_inst[13:11] == (reg2_read_source ? ID_inst[10:8] : ID_inst[7:5])))

  &  
  (MEM_inst[13:11] == (reg2_read_source ? ID_inst[10:8] : ID_inst[7:5]))

)
      forward_B = 2'b10;
    
  end

endmodule

stack.v
`timescale 1ns/1ns
module Stack(input rst, push_sig, pop_sig, clk, input[11:0] push_data, output reg overflow, output reg [11:0] pop_data);
  
  initial begin
    overflow <= 0;
  end

  reg[11:0] data[7:0];
  reg[3:0] stack_pointer = 4'b0;
  
  always @(stack_pointer) begin
    if(stack_pointer != 4'b0) begin
        pop_data = data[stack_pointer - 1];
    end 
  end
  
  always @(posedge clk) begin
  //always @(posedge push_sig) begin
    if(push_sig) begin
      if(stack_pointer == 4'b1000) begin
        overflow <= 1;
      end else begin
        data[stack_pointer] <= push_data;
        stack_pointer <= stack_pointer + 1;
      end
    end
  end
  always @(posedge clk) begin
    if(pop_sig) begin
      if(stack_pointer != 4'b0) begin
        //pop_data <= data[stack_pointer - 1];
        stack_pointer <= stack_pointer - 1;
      end
    end
  end

  integer i;
  initial begin
    for(i = 0; i < 8; i = i + 1) begin: loop2
      $dumpvars(0, data[i]);
    end
  end
  
endmodule

data_memory.v
`timescale 1ns/1ns
module DataMemory(input rst, input[7:0] address, input[7:0] write_data, input read_write, clk, output reg[7:0] read_data);

  reg[7:0] data[255:0];

  always @(posedge clk) begin
    if(read_write & clk)
      data[address] <= write_data;
  end

  always @(address, read_write) begin
    if(read_write == 0) read_data = data[address];
  end

  integer i;
  initial begin
    for(i = 0; i < 6; i = i + 1) begin: loop
      $dumpvars(0, data[100+i]);
    end
  end

endmodule

alu.v
`timescale 1ns/1ns

module ALU(input rst, input signed [7:0] A, input signed [7:0] B, input carry_in, input is_shift, update_z_c, input [1:0] scode, input [2:0] acode, output reg [7:0] R, output reg zero, carry_out);

  function get_carry_out; input [7:0] A, B, C;
    get_carry_out = (A[7]&B[7]) | (A[7]^B[7])&~C[7];
  endfunction



  reg [8:0] temp;
  reg [15:0] temp2;
  reg [7:0] neg_B;
  initial begin
    zero = 0;
    carry_out = 0;
  end
  always @(A, B, scode, acode) begin
    neg_B = -B;
    case(is_shift)
      1'b0: begin
        case(acode)
          3'b000: begin
            temp = A + B;
            if(update_z_c == 1)
              carry_out = get_carry_out(A, B, temp);
          end
          3'b001: begin
            temp = A + B + carry_in; 
            if(update_z_c == 1)
              carry_out = get_carry_out(A, B+carry_in, temp);
          end
          3'b010: begin
            temp = A + ~B + 1;
            if(update_z_c == 1)
              carry_out = get_carry_out(A, -B, temp);
          end
          3'b011: begin
            temp = A + ~B + 1 - carry_in;
            if(update_z_c == 1)
              carry_out = get_carry_out(A, -B + carry_in, temp);
          end

          3'b100: temp = A & B;
          3'b101: temp = A | B;
          3'b110: temp = A ^ B;
          3'b111: temp = ~(A & B);
        endcase
        R = temp[7:0];
      end
      1'b1: 
        if(B == 8'b0)
          R = A;
        else begin
          case(scode)
            2'b00: begin
              carry_out = A[8-B];
              R = A <<< B;
            end
            2'b01: begin
              carry_out = A[B-1];
              R = A >>> B;
            end
            2'b10: begin
              temp2 = {A,A} << (B);
              R = temp2[15:8];
              carry_out = A[7-B];
            end
            2'b11: begin
              temp2 = {A,A} >> (B);
              R = temp2[7:0];
              carry_out = A[B-1];
            end
          endcase
        end
    endcase
    if(update_z_c == 1)
      zero = (R == 8'b0);
  end
endmodule

forward_selector.v
`timescale 1ns/1ns
module ForwardSelector(input[1:0] forward_A, input[1:0] forward_B, input[7:0] ID_data_1, input[7:0] EX_alu_result, input[7:0] mem_or_alu_data, input[7:0] ID_data_2, output reg[7:0] alu_A, output reg[7:0] alu_B);
 
  initial begin
    alu_A = ID_data_1;
    alu_B = ID_data_2;
  end
 
  always @(forward_A, forward_B, ID_data_1, EX_alu_result, mem_or_alu_data, ID_data_2) begin
    case(forward_A)
      2'b00: alu_A = ID_data_1;
      2'b01: alu_A = EX_alu_result;
      2'b10: alu_A = mem_or_alu_data;
    endcase
    
    case(forward_B)
      2'b00: alu_B = ID_data_2;
      2'b01: alu_B = EX_alu_result;
      2'b10: alu_B = mem_or_alu_data;
    endcase
  end

endmodule

register_file.v
`timescale 1ns/1ns
module RegisterFile(input rst, input[2:0] reg_read_1, input [2:0] reg_read_2, input [2:0] reg_write, input reg_write_signal, clk, input[7:0] in_data, output reg [7:0] out_data_1, output reg [7:0] out_data_2);
  
  reg[7:0] registers[7:0];
  always @(posedge clk) begin
    if(reg_write_signal & clk) begin
      registers[reg_write] <= in_data;
    end
  end
  
  initial begin
    out_data_1 = registers[reg_read_1];
    out_data_2 = registers[reg_read_2];
    registers[0] = 0; //$R0
  end
  
  always @(reg_read_1, reg_read_2, registers[reg_read_1], registers[reg_read_2]) begin
    out_data_1 = registers[reg_read_1];
    out_data_2 = registers[reg_read_2];
    registers[0] = 0; //$R0
  end
  
  integer i;
  always @(clk) begin
    for(i = 0; i < 8; i = i + 1) begin: loop
      $display("register[%d]:  %b", i, registers[i]);
    end
  end

  initial begin
    for(i = 0; i < 8; i = i + 1) begin: loop2
      $dumpvars(0, registers[i]);
    end
  end
  
  
endmodule

instruction_memory.v
`timescale 1ns/1ns
module InstructionMemory(input rst, input[11:0] address, output reg[18:0] instruction);
  reg[18:0] instructions[4096:1];

  initial begin
    $readmemb("instructions.mips", instructions);
  end

  always @(address) begin
    instruction = instructions[address];
  end
endmodule

data_path.v
`timescale 1ns/1ns
module DataPath(input rst, reg2_read_source, mem_read_write, mem_or_alu, input is_shift, input alu_src, update_z_c, reg_write_signal, stack_push, stack_pop, clk, input [1:0] pc_src, input [1:0] scode, input [2:0] acode, output zero, stack_overflow, output reg carry, output is_halt, output [18:0] IF_inst);

  reg[11:0] pc = 12'b0;  

  wire[7:0] reg_out_1, reg_out_2; wire alu_carry_out; wire[7:0] alu_result, data_memory_out; wire[11:0] stack_out;
  wire[11:0] incremented_pc;
  wire[11:0] branched_pc;

  wire[18:0] instruction;

  assign incremented_pc = pc + 1;
  assign branched_pc = ID_pc + {{4{ID_inst[7]}},ID_inst[7:0]}; 
  assign is_halt = (MEM_inst == 19'b1111111111111111111);
  always @(posedge clk) begin
    if (ID_update_z_c==1) 
      carry <= alu_carry_out;
      case(EX_pc_src)
        2'b00: pc <= pc + 1;
        2'b01: pc <= IF_inst[11:0];
        2'b10: pc <= stack_out;
        2'b11: pc <= EX_branched_pc;
      endcase
  end

  always @(reg_out_1) begin
    $display("reg_out_1:  %b", reg_out_1);
  end

  /*   IF    */
  reg[11:0] IF_pc; reg[18:0] IF_inst;
  initial begin
    IF_pc = 12'b0;
    IF_inst = 19'b0;
  end
  always @(negedge clk) begin
    #1
    IF_pc <= incremented_pc;
    IF_inst <= instruction;
  end

  /*    ID    */
  reg ID_is_shift;   reg ID_alu_src;   reg ID_update_z_c; 
  reg[1:0] ID_scode; reg[2:0] ID_acode; reg ID_mem_read_write;
  reg[1:0] ID_pc_src = 2'b0;  reg ID_mem_or_alu; reg ID_reg_write_signal;
  reg[11:0] ID_pc; reg[7:0] ID_data_1; reg[7:0] ID_data_2;
  reg[18:0] ID_inst; 
  
  initial begin
    ID_is_shift = 0; ID_alu_src = 0; ID_update_z_c = 0;
    ID_scode = 2'b0; ID_acode = 3'b0; ID_mem_read_write = 0;
    ID_pc_src = 2'b0; ID_mem_or_alu = 0; ID_reg_write_signal = 0;
    ID_pc = 12'b0; ID_data_1 = 8'b0;  ID_data_2 = 8'b0;
    ID_inst = 19'b0;
  end
  always @(negedge clk) begin
    ID_is_shift <= is_shift;     ID_alu_src <= alu_src;
    ID_update_z_c <= update_z_c;     ID_scode <= scode;
    ID_acode <= acode;     ID_mem_read_write <= mem_read_write;
    ID_pc_src <= pc_src;     ID_mem_or_alu <= mem_or_alu;
    ID_reg_write_signal <= reg_write_signal;     ID_pc <= IF_pc;
    ID_data_1 <= reg_out_1;     ID_data_2 <= reg_out_2;
    ID_inst <= IF_inst; 
  end
 
  /*      EX      */
  reg[11:0] EX_branched_pc;  reg[7:0] EX_alu_result;  reg EX_mem_read_write;   
  reg[1:0] EX_pc_src; reg EX_mem_or_alu;   reg EX_reg_write_signal;
  reg[18:0] EX_inst; reg[7:0] EX_data_2;
  initial begin
    EX_branched_pc = 12'b0;
    EX_alu_result = 8'b0;
    EX_mem_read_write = 0;
    EX_pc_src = 2'b0;
    EX_mem_or_alu = 0;
    EX_reg_write_signal = 0;
    EX_inst = 19'b0;
    EX_data_2 = 8'b0;
  end
  always @(negedge clk) begin
    EX_branched_pc <= branched_pc;
    EX_alu_result <= alu_result;
    EX_mem_read_write <= ID_mem_read_write;
    EX_reg_write_signal <= ID_reg_write_signal;
    EX_inst <= ID_inst;
    EX_pc_src <= ID_pc_src;
    EX_mem_or_alu <= ID_mem_or_alu;
    EX_data_2 <= ID_data_2;
  end

  
  /*     MEM     */
    reg[7:0] MEM_alu_result;  reg MEM_reg_write_signal; reg[18:0] MEM_inst; 
    reg MEM_mem_or_alu; reg[7:0] MEM_read_data;
    initial begin
      MEM_alu_result = 8'b0;
      MEM_reg_write_signal = 0;
      MEM_inst = 19'b0;
      MEM_mem_or_alu = 0;
      MEM_read_data = 8'b0;
    end
    always @(negedge clk) begin
      MEM_alu_result <= EX_alu_result;
      MEM_reg_write_signal <= EX_reg_write_signal;
      MEM_inst <= EX_inst;
      MEM_mem_or_alu <= EX_mem_or_alu;
      MEM_read_data <= data_memory_out;
    end
  
  InstructionMemory instruction_memory(rst, pc, instruction);

  
  RegisterFile register_file(rst, IF_inst[10:8], reg2_read_source ? IF_inst[13:11] : IF_inst[7:5], MEM_inst[13:11], MEM_reg_write_signal, clk, MEM_mem_or_alu ? MEM_alu_result : MEM_read_data, reg_out_1, reg_out_2);


  wire[7:0] alu_A; wire[7:0] alu_B;
  ForwardSelector forward_selector(forward_A, forward_B, ID_data_1, EX_alu_result, MEM_mem_or_alu ? MEM_alu_result : MEM_read_data, ( ID_is_shift ? {5'b0,ID_inst[7:5]} : ID_data_2), alu_A, alu_B);
  
  ALU alu(rst, alu_A, (ID_alu_src ? ID_inst[7:0] : alu_B), carry, ID_is_shift, ID_update_z_c, ID_scode, ID_acode, alu_result, zero, alu_carry_out);

  DataMemory data_memory(rst, EX_alu_result, EX_data_2, EX_mem_read_write, clk, data_memory_out);

  Stack stack(rst, stack_push, stack_pop, clk, IF_pc + {11'b0,1'b1}, stack_overflow, stack_out);

  wire[1:0] forward_A; wire[1:0]forward_B;
  ForwardingUnit forwarding_unit(reg2_read_source, EX_reg_write_signal, EX_inst, ID_inst, MEM_reg_write_signal, MEM_inst, forward_A, forward_B);

endmodule

CPU.v
`timescale 1ns/1ns
module MIPSCPU(input clk, rst, output zero, carry, stack_overflow);
  wire reg2_read_source, mem_read_write, mem_or_alu;
  wire is_shift;
  wire is_halt;
  wire alu_src, update_z_c, reg_read_write, stack_pushs, stack_pop;
  wire [1:0] pc_src, scode;
  wire [2:0] acode;
  wire [18:0] instruction;

  DataPath data_path(rst, reg2_read_source, mem_read_write, mem_or_alu, is_shift, alu_src, update_z_c, reg_read_write, stack_push, stack_pop, clk, pc_src, scode, acode, zero, stack_overflow, carry, is_halt, instruction);

  Controller controller(rst, zero, carry, clk, is_halt, instruction, reg2_read_source, mem_read_write, mem_or_alu, is_shift, alu_src, update_z_c, reg_read_write, stack_push, stack_pop, pc_src, scode, acode);

endmodule

tests/CPU_test.v
`timescale 1ns/1ns

module CPUTest;
  reg clk = 1, rst;
  wire zero, carry, stack_overflow;

  MIPSCPU cpu(clk, rst, zero, carry, stack_overflow);
  initial begin
    clk = 1;
  end
  always begin
    #20 clk = ~clk;
    //if(clk == 1) begin
      //$display("");
      //$display("-------------------------------------------------------");
      //$display("a clock pulse passed!");
      //$display("-------------------------------------------------------");
      //$display("");
    //end
  end

  initial begin
    $dumpfile("cpu.vcd");
    $dumpvars(0, CPUTest);
  end
endmodule

dump.vcd
$date
	Wed May 20 14:50:52 2015
$end
$version
	Icarus Verilog
$end
$timescale
	1ns
$end
$scope module CPUTest $end
$scope module cpu $end
$scope module data_path $end
$scope module register_file $end
$var reg 8 ! \registers[0] [7:0] $end
$upscope $end
$upscope $end
$upscope $end
$upscope $end
$scope module CPUTest $end
$scope module cpu $end
$scope module data_path $end
$scope module register_file $end
$var reg 8 " \registers[1] [7:0] $end
$upscope $end
$upscope $end
$upscope $end
$upscope $end
$scope module CPUTest $end
$scope module cpu $end
$scope module data_path $end
$scope module register_file $end
$var reg 8 # \registers[2] [7:0] $end
$upscope $end
$upscope $end
$upscope $end
$upscope $end
$scope module CPUTest $end
$scope module cpu $end
$scope module data_path $end
$scope module register_file $end
$var reg 8 $ \registers[3] [7:0] $end
$upscope $end
$upscope $end
$upscope $end
$upscope $end
$scope module CPUTest $end
$scope module cpu $end
$scope module data_path $end
$scope module register_file $end
$var reg 8 % \registers[4] [7:0] $end
$upscope $end
$upscope $end
$upscope $end
$upscope $end
$scope module CPUTest $end
$scope module cpu $end
$scope module data_path $end
$scope module register_file $end
$var reg 8 & \registers[5] [7:0] $end
$upscope $end
$upscope $end
$upscope $end
$upscope $end
$scope module CPUTest $end
$scope module cpu $end
$scope module data_path $end
$scope module register_file $end
$var reg 8 ' \registers[6] [7:0] $end
$upscope $end
$upscope $end
$upscope $end
$upscope $end
$scope module CPUTest $end
$scope module cpu $end
$scope module data_path $end
$scope module register_file $end
$var reg 8 ( \registers[7] [7:0] $end
$upscope $end
$upscope $end
$upscope $end
$upscope $end
$scope module CPUTest $end
$scope module cpu $end
$scope module data_path $end
$scope module data_memory $end
$var reg 8 ) \data[100] [7:0] $end
$upscope $end
$upscope $end
$upscope $end
$upscope $end
$scope module CPUTest $end
$scope module cpu $end
$scope module data_path $end
$scope module data_memory $end
$var reg 8 * \data[101] [7:0] $end
$upscope $end
$upscope $end
$upscope $end
$upscope $end
$scope module CPUTest $end
$scope module cpu $end
$scope module data_path $end
$scope module data_memory $end
$var reg 8 + \data[102] [7:0] $end
$upscope $end
$upscope $end
$upscope $end
$upscope $end
$scope module CPUTest $end
$scope module cpu $end
$scope module data_path $end
$scope module data_memory $end
$var reg 8 , \data[103] [7:0] $end
$upscope $end
$upscope $end
$upscope $end
$upscope $end
$scope module CPUTest $end
$scope module cpu $end
$scope module data_path $end
$scope module data_memory $end
$var reg 8 - \data[104] [7:0] $end
$upscope $end
$upscope $end
$upscope $end
$upscope $end
$scope module CPUTest $end
$scope module cpu $end
$scope module data_path $end
$scope module data_memory $end
$var reg 8 . \data[105] [7:0] $end
$upscope $end
$upscope $end
$upscope $end
$upscope $end
$scope module CPUTest $end
$scope module cpu $end
$scope module data_path $end
$scope module stack $end
$var reg 12 / \data[0] [11:0] $end
$upscope $end
$upscope $end
$upscope $end
$upscope $end
$scope module CPUTest $end
$scope module cpu $end
$scope module data_path $end
$scope module stack $end
$var reg 12 0 \data[1] [11:0] $end
$upscope $end
$upscope $end
$upscope $end
$upscope $end
$scope module CPUTest $end
$scope module cpu $end
$scope module data_path $end
$scope module stack $end
$var reg 12 1 \data[2] [11:0] $end
$upscope $end
$upscope $end
$upscope $end
$upscope $end
$scope module CPUTest $end
$scope module cpu $end
$scope module data_path $end
$scope module stack $end
$var reg 12 2 \data[3] [11:0] $end
$upscope $end
$upscope $end
$upscope $end
$upscope $end
$scope module CPUTest $end
$scope module cpu $end
$scope module data_path $end
$scope module stack $end
$var reg 12 3 \data[4] [11:0] $end
$upscope $end
$upscope $end
$upscope $end
$upscope $end
$scope module CPUTest $end
$scope module cpu $end
$scope module data_path $end
$scope module stack $end
$var reg 12 4 \data[5] [11:0] $end
$upscope $end
$upscope $end
$upscope $end
$upscope $end
$scope module CPUTest $end
$scope module cpu $end
$scope module data_path $end
$scope module stack $end
$var reg 12 5 \data[6] [11:0] $end
$upscope $end
$upscope $end
$upscope $end
$upscope $end
$scope module CPUTest $end
$scope module cpu $end
$scope module data_path $end
$scope module stack $end
$var reg 12 6 \data[7] [11:0] $end
$upscope $end
$upscope $end
$upscope $end
$upscope $end
$scope module CPUTest $end
$var wire 1 7 carry $end
$var wire 1 8 stack_overflow $end
$var wire 1 9 zero $end
$var reg 1 : clk $end
$var reg 1 ; rst $end
$scope module cpu $end
$var wire 3 < acode [2:0] $end
$var wire 1 = alu_src $end
$var wire 1 7 carry $end
$var wire 1 > clk $end
$var wire 19 ? instruction [18:0] $end
$var wire 1 @ is_halt $end
$var wire 1 A is_shift $end
$var wire 1 B mem_or_alu $end
$var wire 1 C mem_read_write $end
$var wire 2 D pc_src [1:0] $end
$var wire 1 E reg2_read_source $end
$var wire 1 F reg_read_write $end
$var wire 1 G rst $end
$var wire 2 H scode [1:0] $end
$var wire 1 8 stack_overflow $end
$var wire 1 I stack_pop $end
$var wire 1 J stack_push $end
$var wire 1 K update_z_c $end
$var wire 1 9 zero $end
$scope module data_path $end
$var wire 3 L acode [2:0] $end
$var wire 8 M alu_A [7:0] $end
$var wire 8 N alu_B [7:0] $end
$var wire 1 O alu_carry_out $end
$var wire 8 P alu_result [7:0] $end
$var wire 1 = alu_src $end
$var wire 12 Q branched_pc [11:0] $end
$var wire 1 > clk $end
$var wire 8 R data_memory_out [7:0] $end
$var wire 2 S forward_A [1:0] $end
$var wire 2 T forward_B [1:0] $end
$var wire 12 U incremented_pc [11:0] $end
$var wire 19 V instruction [18:0] $end
$var wire 1 @ is_halt $end
$var wire 1 A is_shift $end
$var wire 1 B mem_or_alu $end
$var wire 1 C mem_read_write $end
$var wire 2 W pc_src [1:0] $end
$var wire 1 E reg2_read_source $end
$var wire 8 X reg_out_1 [7:0] $end
$var wire 8 Y reg_out_2 [7:0] $end
$var wire 1 F reg_write_signal $end
$var wire 1 G rst $end
$var wire 2 Z scode [1:0] $end
$var wire 12 [ stack_out [11:0] $end
$var wire 1 8 stack_overflow $end
$var wire 1 I stack_pop $end
$var wire 1 J stack_push $end
$var wire 1 K update_z_c $end
$var wire 1 9 zero $end
$var reg 8 \ EX_alu_result [7:0] $end
$var reg 12 ] EX_branched_pc [11:0] $end
$var reg 8 ^ EX_data_2 [7:0] $end
$var reg 19 _ EX_inst [18:0] $end
$var reg 1 ` EX_mem_or_alu $end
$var reg 1 a EX_mem_read_write $end
$var reg 2 b EX_pc_src [1:0] $end
$var reg 1 c EX_reg_write_signal $end
$var reg 3 d ID_acode [2:0] $end
$var reg 1 e ID_alu_src $end
$var reg 8 f ID_data_1 [7:0] $end
$var reg 8 g ID_data_2 [7:0] $end
$var reg 19 h ID_inst [18:0] $end
$var reg 1 i ID_is_shift $end
$var reg 1 j ID_mem_or_alu $end
$var reg 1 k ID_mem_read_write $end
$var reg 12 l ID_pc [11:0] $end
$var reg 2 m ID_pc_src [1:0] $end
$var reg 1 n ID_reg_write_signal $end
$var reg 2 o ID_scode [1:0] $end
$var reg 1 p ID_update_z_c $end
$var reg 19 q IF_inst [18:0] $end
$var reg 12 r IF_pc [11:0] $end
$var reg 8 s MEM_alu_result [7:0] $end
$var reg 19 t MEM_inst [18:0] $end
$var reg 1 u MEM_mem_or_alu $end
$var reg 8 v MEM_read_data [7:0] $end
$var reg 1 w MEM_reg_write_signal $end
$var reg 1 x carry $end
$var reg 12 y pc [11:0] $end
$scope module instruction_memory $end
$var wire 12 z address [11:0] $end
$var wire 1 G rst $end
$var reg 19 { instruction [18:0] $end
$upscope $end
$scope module register_file $end
$var wire 1 > clk $end
$var wire 8 | in_data [7:0] $end
$var wire 3 } reg_read_1 [2:0] $end
$var wire 3 ~ reg_read_2 [2:0] $end
$var wire 3 !" reg_write [2:0] $end
$var wire 1 "" reg_write_signal $end
$var wire 1 G rst $end
$var integer 32 #" i [31:0] $end
$var reg 8 $" out_data_1 [7:0] $end
$var reg 8 %" out_data_2 [7:0] $end
$scope begin loop $end
$upscope $end
$scope begin loop2 $end
$upscope $end
$upscope $end
$scope module forward_selector $end
$var wire 8 &" EX_alu_result [7:0] $end
$var wire 8 '" ID_data_1 [7:0] $end
$var wire 8 (" ID_data_2 [7:0] $end
$var wire 2 )" forward_A [1:0] $end
$var wire 2 *" forward_B [1:0] $end
$var wire 8 +" mem_or_alu_data [7:0] $end
$var reg 8 ," alu_A [7:0] $end
$var reg 8 -" alu_B [7:0] $end
$upscope $end
$scope module alu $end
$var wire 8 ." A [7:0] $end
$var wire 8 /" B [7:0] $end
$var wire 3 0" acode [2:0] $end
$var wire 1 7 carry_in $end
$var wire 1 1" is_shift $end
$var wire 1 G rst $end
$var wire 2 2" scode [1:0] $end
$var wire 1 3" update_z_c $end
$var reg 8 4" R [7:0] $end
$var reg 1 5" carry_out $end
$var reg 8 6" neg_B [7:0] $end
$var reg 9 7" temp [8:0] $end
$var reg 16 8" temp2 [15:0] $end
$var reg 1 9" zero $end
$scope function get_carry_out $end
$var reg 8 :" A [7:0] $end
$var reg 8 ;" B [7:0] $end
$var reg 8 <" C [7:0] $end
$var reg 1 =" get_carry_out $end
$upscope $end
$upscope $end
$scope module data_memory $end
$var wire 8 >" address [7:0] $end
$var wire 1 > clk $end
$var wire 1 ?" read_write $end
$var wire 1 G rst $end
$var wire 8 @" write_data [7:0] $end
$var integer 32 A" i [31:0] $end
$var reg 8 B" read_data [7:0] $end
$scope begin loop $end
$upscope $end
$upscope $end
$scope module stack $end
$var wire 1 > clk $end
$var wire 1 I pop_sig $end
$var wire 12 C" push_data [11:0] $end
$var wire 1 J push_sig $end
$var wire 1 G rst $end
$var integer 32 D" i [31:0] $end
$var reg 1 E" overflow $end
$var reg 12 F" pop_data [11:0] $end
$var reg 4 G" stack_pointer [3:0] $end
$scope begin loop2 $end
$upscope $end
$upscope $end
$scope module forwarding_unit $end
$var wire 19 H" EX_inst [18:0] $end
$var wire 1 I" EX_reg_write_signal $end
$var wire 19 J" ID_inst [18:0] $end
$var wire 19 K" MEM_inst [18:0] $end
$var wire 1 "" MEM_reg_write_signal $end
$var wire 1 E reg2_read_source $end
$var reg 2 L" forward_A [1:0] $end
$var reg 2 M" forward_B [1:0] $end
$upscope $end
$upscope $end
$scope module controller $end
$var wire 1 7 carry $end
$var wire 1 > clk $end
$var wire 19 N" instruction [18:0] $end
$var wire 1 @ is_halt $end
$var wire 1 G rst $end
$var wire 1 9 zero $end
$var reg 3 O" acode [2:0] $end
$var reg 1 P" alu_src $end
$var reg 1 Q" is_shift $end
$var reg 1 R" mem_or_alu $end
$var reg 1 S" mem_read_write $end
$var reg 2 T" pc_src [1:0] $end
$var reg 1 U" reg2_read_source $end
$var reg 1 V" reg_write_signal $end
$var reg 2 W" scode [1:0] $end
$var reg 1 X" stack_pop $end
$var reg 1 Y" stack_push $end
$var reg 1 Z" update_z_c $end
$upscope $end
$upscope $end
$upscope $end
$enddefinitions $end
#0
$dumpvars
1Z"
0Y"
0X"
b0 W"
1V"
0U"
b0 T"
0S"
1R"
0Q"
0P"
b0 O"
b0 N"
b0 M"
b0 L"
b0 K"
b0 J"
0I"
b0 H"
b0 G"
bx F"
0E"
b1000 D"
b1 C"
bx B"
b110 A"
b0 @"
0?"
b0 >"
x="
bx <"
bx ;"
bx :"
09"
bx 8"
b0 7"
b0 6"
05"
b0 4"
03"
b0 2"
01"
b0 0"
b0 /"
b0 ."
b0 -"
b0 ,"
b0 +"
b0 *"
b0 )"
b0 ("
b0 '"
b0 &"
b0 %"
b0 $"
b1000 #"
0""
b0 !"
b0 ~
b0 }
b0 |
b100000100000000001 {
b1 z
b1 y
xx
0w
b0 v
0u
b0 t
b0 s
b0 r
b0 q
0p
b0 o
0n
b0 m
b0 l
0k
0j
0i
b0 h
b0 g
b0 f
0e
b0 d
0c
b0 b
0a
0`
b0 _
b0 ^
b0 ]
b0 \
bx [
b0 Z
b0 Y
b0 X
b0 W
b100000100000000001 V
b10 U
b0 T
b0 S
bx R
b0 Q
b0 P
0O
b0 N
b0 M
b0 L
1K
0J
0I
b0 H
xG
1F
0E
b0 D
0C
1B
0A
0@
b0 ?
1>
0=
b0 <
x;
1:
09
08
x7
bx 6
bx 5
bx 4
bx 3
bx 2
bx 1
bx 0
bx /
bx .
bx -
bx ,
bx +
bx *
bx )
bx (
bx '
bx &
bx %
bx $
bx #
bx "
b0 !
$end
#20
bx |
bx +"
1n
1j
1p
13"
bx v
b1000 #"
0:
0>
#21
1P"
1=
1Z"
1K
1V"
1F
1R"
1B
b100000100000000001 q
b100000100000000001 ?
b100000100000000001 N"
b10 r
b11 C"
#40
b11 U
b100001000000000010 {
b100001000000000010 V
1Z"
1K
1V"
1F
1P"
1=
1R"
1B
b10 y
b10 z
0x
07
b1000 #"
1:
1>
#60
b1 4"
b1 P
0="
b1 <"
b1 ;"
b0 :"
b1 7"
b11111111 6"
b1 /"
1`
1c
1I"
b100000100000000001 h
b100000100000000001 J"
b10 l
b11 Q
1e
b1000 #"
0:
0>
#61
1Z"
1K
1V"
1F
1P"
1=
1R"
1B
b100001000000000010 q
b100001000000000010 ?
b100001000000000010 N"
b11 r
b100 C"
#80
b100 U
b1100101000000 {
b1100101000000 V
1Z"
1K
1V"
1F
1P"
1=
1R"
1B
b11 y
b11 z
b1000 #"
1:
1>
#100
b10 4"
b10 P
b10 <"
b10 ;"
b10 7"
b11111110 6"
b10 /"
b0 |
b0 +"
b100001000000000010 h
b100001000000000010 J"
b11 l
b101 Q
b100000100000000001 _
b100000100000000001 H"
b1 \
b1 &"
b1 >"
b11 ]
1u
1w
1""
b1000 #"
0:
0>
#101
1Z"
1K
1V"
1F
0P"
0=
1R"
1B
b0 !
bx %"
bx Y
bx $"
bx X
b10 ~
b1 }
b1100101000000 q
b1100101000000 ?
b1100101000000 N"
b100 r
b101 C"
